<?xml version="1.0" encoding="UTF-8" standalone="yes"?>
<FaultSourceSet id="-1" name="ut.3dip.gr" weight="0.3334">
  <!-- Original source file: ut.3dip.gr.in -->
  <Settings>
    <DefaultMfds>
      <IncrementalMfd a="0.0" floats="false" m="6.5" type="SINGLE" weight="1.0"/>
      <IncrementalMfd a="0.0" b="0.8" dMag="0.1" mMax="7.5" mMin="6.55" type="GR" weight="1.0"/>
    </DefaultMfds>
    <MagUncertainty>
      <Epistemic cutoff="6.5" deltas="[-0.2, 0.0, 0.2]" weights="[0.2, 0.6, 0.2]"/>
    </MagUncertainty>
    <SourceProperties ruptureScaling="NSHM_FAULT_WC94_LENGTH"/>
  </Settings>
  <Source id="272" name="East Cache 50">
    <IncrementalMfd a="1.2883028" dMag="0.10124999" mMax="7.259475005" mMin="6.550624995" type="GR" weight="0.6"/>
    <Geometry depth="0.0" dip="50.0" rake="-90.0" width="19.58112">
      <Trace>
-111.69625,42.13224,0.00000
-111.72994,42.04950,0.00000
-111.73632,42.00063,0.00000
-111.76256,41.97511,0.00000
-111.78744,41.93289,0.00000
-111.79382,41.91411,0.00000
-111.78960,41.90944,0.00000
-111.79112,41.89489,0.00000
-111.80235,41.88015,0.00000
-111.81458,41.87575,0.00000
-111.79067,41.83119,0.00000
-111.77531,41.78025,0.00000
-111.79095,41.74360,0.00000
-111.80559,41.64073,0.00000
-111.79903,41.61729,0.00000
-111.78367,41.59429,0.00000
-111.77531,41.49995,0.00000
-111.75959,41.44758,0.00000
-111.76534,41.42189,0.00000
</Trace>
    </Geometry>
  </Source>
  <Source id="273" name="Morgan 50">
    <IncrementalMfd a="4.0710369e-05" floats="true" m="6.51" type="SINGLE" weight="0.6"/>
    <Geometry depth="0.0" dip="50.0" rake="-90.0" width="19.58112">
      <Trace>
-111.72213,41.15147,0.00000
-111.70596,41.10673,0.00000
-111.67146,41.07663,0.00000
-111.66795,41.02731,0.00000
-111.65457,41.00961,0.00000
</Trace>
    </Geometry>
  </Source>
  <Source id="275" name="North Promontory 50">
    <IncrementalMfd a="1.6267301" dMag="0.11500001" mMax="6.672599995000001" mMin="6.557500005" type="GR" weight="0.6"/>
    <Geometry depth="0.0" dip="50.0" rake="-90.0" width="19.58112">
      <Trace>
-112.54981,41.90154,0.00000
-112.54937,41.87926,0.00000
-112.55628,41.85455,0.00000
-112.55476,41.78897,0.00000
-112.55952,41.76606,0.00000
-112.59357,41.69922,0.00000
-112.61729,41.67361,0.00000
</Trace>
    </Geometry>
  </Source>
  <Source id="277" name="Great Salt Lake - Promontory section 50">
    <IncrementalMfd a="1.793224" dMag="0.09833336" mMax="7.04093332" mMin="6.54916668" type="GR" weight="0.6"/>
    <Geometry depth="0.0" dip="50.0" rake="-90.0" width="19.58112">
      <Trace>
-112.83550,41.53418,0.00000
-112.80316,41.49349,0.00000
-112.77477,41.46743,0.00000
-112.70416,41.43572,0.00000
-112.65448,41.39826,0.00000
-112.57551,41.38820,0.00000
-112.54659,41.37562,0.00000
-112.53293,41.34651,0.00000
-112.51271,41.32450,0.00000
-112.51181,41.26314,0.00000
-112.50211,41.23700,0.00000
-112.48944,41.21498,0.00000
-112.45800,41.19190,0.00000
</Trace>
    </Geometry>
  </Source>
  <Source id="278" name="Great Salt Lake - Fremont Island section 50">
    <IncrementalMfd a="1.8456042" dMag="0.08249998" mMax="6.78885001" mMin="6.54124999" type="GR" weight="0.6"/>
    <Geometry depth="0.0" dip="50.0" rake="-90.0" width="19.58112">
      <Trace>
-112.52106,41.21004,0.00000
-112.51936,41.19926,0.00000
-112.49142,41.17833,0.00000
-112.45189,41.17132,0.00000
-112.44012,41.16162,0.00000
-112.41326,41.15156,0.00000
-112.36376,41.09325,0.00000
-112.35370,41.06019,0.00000
-112.32657,41.02605,0.00000
-112.31839,41.00368,0.00000
-112.30527,40.99272,0.00000
</Trace>
    </Geometry>
  </Source>
  <Source id="279" name="Great Salt Lake - Antelope Island section 50">
    <IncrementalMfd a="1.8982953" dMag="0.10749996" mMax="6.876350019999999" mMin="6.55374998" type="GR" weight="0.6"/>
    <Geometry depth="0.0" dip="50.0" rake="-90.0" width="19.58112">
      <Trace>
-112.31893,41.03441,0.00000
-112.30114,41.01222,0.00000
-112.26485,40.98913,0.00000
-112.27149,40.96613,0.00000
-112.26916,40.94448,0.00000
-112.23646,40.87027,0.00000
-112.21624,40.85455,0.00000
-112.18363,40.81915,0.00000
-112.19486,40.79391,0.00000
-112.20348,40.75051,0.00000
-112.21373,40.73408,0.00000
-112.22972,40.72392,0.00000
</Trace>
    </Geometry>
  </Source>
  <Source id="281" name="Stansbury 50">
    <IncrementalMfd a="1.6193315" dMag="0.09833336" mMax="7.04093332" mMin="6.54916668" type="GR" weight="0.6"/>
    <Geometry depth="0.0" dip="50.0" rake="-90.0" width="19.58112">
      <Trace>
-112.65942,40.68951,0.00000
-112.68340,40.59402,0.00000
-112.67119,40.54227,0.00000
-112.66427,40.53490,0.00000
-112.68449,40.50166,0.00000
-112.69230,40.47552,0.00000
-112.67873,40.43105,0.00000
-112.68026,40.42449,0.00000
-112.66499,40.39466,0.00000
-112.54541,40.27617,0.00000
-112.52520,40.25020,0.00000
</Trace>
    </Geometry>
  </Source>
  <Source id="282" name="Oquirrh - Southern Oquirrh Mountains 50">
    <IncrementalMfd a="1.3553717" dMag="0.11166668" mMax="7.114266659999999" mMin="6.55583334" type="GR" weight="0.6"/>
    <Geometry depth="0.0" dip="50.0" rake="-90.0" width="19.58112">
      <Trace>
-112.25326,40.69473,0.00000
-112.24660,40.68619,0.00000
-112.24409,40.65295,0.00000
-112.25452,40.64963,0.00000
-112.25622,40.64118,0.00000
-112.26305,40.63795,0.00000
-112.25883,40.63148,0.00000
-112.25703,40.60462,0.00000
-112.20034,40.55548,0.00000
-112.20034,40.54433,0.00000
-112.23906,40.53526,0.00000
-112.25784,40.51774,0.00000
-112.30430,40.50078,0.00000
-112.34476,40.45990,0.00000
-112.31691,40.40194,0.00000
-112.27478,40.30910,0.00000
-112.25825,40.27052,0.00000
-112.22314,40.22889,0.00000
</Trace>
    </Geometry>
  </Source>
  <Source id="283" name="Strawberry 50">
    <IncrementalMfd a="1.1174334" dMag="0.10500002" mMax="6.8675999899999995" mMin="6.55250001" type="GR" weight="0.6"/>
    <Geometry depth="0.0" dip="50.0" rake="-90.0" width="19.58112">
      <Trace>
-111.21238,40.28982,0.00000
-111.18471,40.28928,0.00000
-111.16782,40.28362,0.00000
-111.14132,40.25730,0.00000
-111.10744,40.25209,0.00000
-111.10313,40.23808,0.00000
-111.10080,40.20178,0.00000
-111.11419,40.16782,0.00000
-111.11140,40.15371,0.00000
-111.11913,40.14338,0.00000
-111.11598,40.12236,0.00000
-111.14213,40.09047,0.00000
-111.14706,40.05615,0.00000
-111.13862,40.00755,0.00000
</Trace>
    </Geometry>
  </Source>
  <Source id="285" name="West Cache - Clarkston section 50">
    <IncrementalMfd a="1.8939321" dMag="0.07999992" mMax="6.62010004" mMin="6.53999996" type="GR" weight="0.6"/>
    <Geometry depth="0.0" dip="50.0" rake="-90.0" width="19.58112">
      <Trace>
-112.06657,41.89625,0.00000
-112.07013,41.89819,0.00000
-112.08070,41.91283,0.00000
-112.08927,41.92109,0.00000
-112.09216,41.93003,0.00000
-112.09834,41.93920,0.00000
-112.10303,41.94943,0.00000
-112.10191,41.95312,0.00000
-112.11048,41.97083,0.00000
-112.10936,41.98233,0.00000
-112.10979,41.99078,0.00000
-112.10667,41.99516,0.00000
-112.09572,41.99985,0.00000
-112.09353,42.00871,0.00000
-112.09103,42.01321,0.00000
-112.09065,42.03051,0.00000
-112.08408,42.05125,0.00000
-112.08076,42.07558,0.00000
-112.07820,42.08941,0.00000
</Trace>
    </Geometry>
  </Source>
  <Source id="286" name="West Cache - Wellsville section 50">
    <IncrementalMfd a="0.00020886566" floats="true" m="6.55" type="SINGLE" weight="0.6"/>
    <Geometry depth="0.0" dip="50.0" rake="-90.0" width="19.58112">
      <Trace>
-111.87531,41.57973,0.00000
-111.91807,41.60130,0.00000
-111.95148,41.62492,0.00000
-111.99946,41.68979,0.00000
-112.00980,41.69670,0.00000
-112.02291,41.72105,0.00000
</Trace>
    </Geometry>
  </Source>
  <Source id="287" name="Paragonah 50">
    <IncrementalMfd a="1.995324" dMag="0.125" mMax="6.6876" mMin="6.5625" type="GR" weight="0.6"/>
    <Geometry depth="0.0" dip="50.0" rake="-90.0" width="19.58112">
      <Trace>
-112.70164,37.97835,0.00000
-112.71494,37.94951,0.00000
-112.74746,37.91241,0.00000
-112.75195,37.88995,0.00000
-112.78816,37.83784,0.00000
-112.84296,37.80253,0.00000
-112.86929,37.77684,0.00000
</Trace>
    </Geometry>
  </Source>
  <Source id="477" name="Sevier - Toroweap (northern) 50">
    <IncrementalMfd a="1.5575325" dMag="0.10374999" mMax="7.2782250049999995" mMin="6.551874995" type="GR" weight="0.6"/>
    <Geometry depth="0.0" dip="50.0" rake="-90.0" width="19.58112">
      <Trace>
-112.29620,37.87458,0.00000
-112.33034,37.79678,0.00000
-112.33267,37.77298,0.00000
-112.32729,37.72680,0.00000
-112.33250,37.68412,0.00000
-112.35397,37.66499,0.00000
-112.37382,37.63597,0.00000
-112.38424,37.60291,0.00000
-112.39547,37.58575,0.00000
-112.40212,37.55566,0.00000
-112.42107,37.52242,0.00000
-112.52861,37.37975,0.00000
-112.53661,37.37894,0.00000
-112.54497,37.37122,0.00000
-112.55170,37.35289,0.00000
-112.56132,37.34085,0.00000
-112.56913,37.33752,0.00000
-112.62331,37.27886,0.00000
-112.66005,37.20268,0.00000
-112.66517,37.16908,0.00000
</Trace>
    </Geometry>
  </Source>
  <Source id="479" name="Hurricane (northern) 50">
    <IncrementalMfd a="1.2834035" dMag="0.086666665" mMax="6.9767666675" mMin="6.5433333325" type="GR" weight="0.6"/>
    <Geometry depth="0.0" dip="50.0" rake="-90.0" width="19.58112">
      <Trace>
-113.05462,37.66077,0.00000
-113.09164,37.61567,0.00000
-113.10520,37.58944,0.00000
-113.12784,37.56922,0.00000
-113.14509,37.56536,0.00000
-113.16396,37.55206,0.00000
-113.19738,37.50121,0.00000
-113.21436,37.48882,0.00000
-113.23026,37.42386,0.00000
-113.22775,37.40374,0.00000
-113.26620,37.33483,0.00000
-113.28227,37.29701,0.00000
</Trace>
    </Geometry>
  </Source>
  <Source id="274" name="Hansel Valley 50">
    <IncrementalMfd a="0.00013429499" floats="true" m="6.55" type="SINGLE" weight="0.6"/>
    <Geometry depth="0.0" dip="50.0" rake="-90.0" width="19.58112">
      <Trace>
-112.75555,41.68394,0.00000
-112.74863,41.71027,0.00000
-112.73273,41.73938,0.00000
-112.72842,41.78097,0.00000
-112.72060,41.79813,0.00000
</Trace>
    </Geometry>
  </Source>
  <Source id="284" name="Joes Valley 50">
    <IncrementalMfd a="1.4678782" dMag="0.125" mMax="6.9376" mMin="6.5625" type="GR" weight="0.6"/>
    <Geometry depth="0.0" dip="50.0" rake="-90.0" width="19.58112">
      <Trace>
-111.22218,39.59977,0.00000
-111.21831,39.53122,0.00000
-111.23071,39.50013,0.00000
-111.22810,39.46815,0.00000
-111.23260,39.43150,0.00000
-111.25721,39.35990,0.00000
-111.27042,39.30213,0.00000
-111.26961,39.25838,0.00000
-111.25739,39.18471,0.00000
</Trace>
    </Geometry>
  </Source>
  <Source id="272" name="East Cache 40">
    <IncrementalMfd a="1.4406757" dMag="0.10124999" mMax="7.259475005" mMin="6.550624995" type="GR" weight="0.2"/>
    <Geometry depth="0.0" dip="40.0" rake="-90.0" width="23.33587">
      <Trace>
-111.69625,42.13224,0.00000
-111.72994,42.04950,0.00000
-111.73632,42.00063,0.00000
-111.76256,41.97511,0.00000
-111.78744,41.93289,0.00000
-111.79382,41.91411,0.00000
-111.78960,41.90944,0.00000
-111.79112,41.89489,0.00000
-111.80235,41.88015,0.00000
-111.81458,41.87575,0.00000
-111.79067,41.83119,0.00000
-111.77531,41.78025,0.00000
-111.79095,41.74360,0.00000
-111.80559,41.64073,0.00000
-111.79903,41.61729,0.00000
-111.78367,41.59429,0.00000
-111.77531,41.49995,0.00000
-111.75959,41.44758,0.00000
-111.76534,41.42189,0.00000
</Trace>
    </Geometry>
  </Source>
  <Source id="273" name="Morgan 40">
    <IncrementalMfd a="5.7819996e-05" floats="true" m="6.51" type="SINGLE" weight="0.2"/>
    <Geometry depth="0.0" dip="40.0" rake="-90.0" width="23.33587">
      <Trace>
-111.72213,41.15147,0.00000
-111.70596,41.10673,0.00000
-111.67146,41.07663,0.00000
-111.66795,41.02731,0.00000
-111.65457,41.00961,0.00000
</Trace>
    </Geometry>
  </Source>
  <Source id="275" name="North Promontory 40">
    <IncrementalMfd a="1.779103" dMag="0.11500001" mMax="6.672599995000001" mMin="6.557500005" type="GR" weight="0.2"/>
    <Geometry depth="0.0" dip="40.0" rake="-90.0" width="23.33587">
      <Trace>
-112.54981,41.90154,0.00000
-112.54937,41.87926,0.00000
-112.55628,41.85455,0.00000
-112.55476,41.78897,0.00000
-112.55952,41.76606,0.00000
-112.59357,41.69922,0.00000
-112.61729,41.67361,0.00000
</Trace>
    </Geometry>
  </Source>
  <Source id="277" name="Great Salt Lake - Promontory section 40">
    <IncrementalMfd a="1.9455969" dMag="0.09833336" mMax="7.04093332" mMin="6.54916668" type="GR" weight="0.2"/>
    <Geometry depth="0.0" dip="40.0" rake="-90.0" width="23.33587">
      <Trace>
-112.83550,41.53418,0.00000
-112.80316,41.49349,0.00000
-112.77477,41.46743,0.00000
-112.70416,41.43572,0.00000
-112.65448,41.39826,0.00000
-112.57551,41.38820,0.00000
-112.54659,41.37562,0.00000
-112.53293,41.34651,0.00000
-112.51271,41.32450,0.00000
-112.51181,41.26314,0.00000
-112.50211,41.23700,0.00000
-112.48944,41.21498,0.00000
-112.45800,41.19190,0.00000
</Trace>
    </Geometry>
  </Source>
  <Source id="278" name="Great Salt Lake - Fremont Island section 40">
    <IncrementalMfd a="1.9979771" dMag="0.08249998" mMax="6.78885001" mMin="6.54124999" type="GR" weight="0.2"/>
    <Geometry depth="0.0" dip="40.0" rake="-90.0" width="23.33587">
      <Trace>
-112.52106,41.21004,0.00000
-112.51936,41.19926,0.00000
-112.49142,41.17833,0.00000
-112.45189,41.17132,0.00000
-112.44012,41.16162,0.00000
-112.41326,41.15156,0.00000
-112.36376,41.09325,0.00000
-112.35370,41.06019,0.00000
-112.32657,41.02605,0.00000
-112.31839,41.00368,0.00000
-112.30527,40.99272,0.00000
</Trace>
    </Geometry>
  </Source>
  <Source id="279" name="Great Salt Lake - Antelope Island section 40">
    <IncrementalMfd a="2.0506682" dMag="0.10749996" mMax="6.876350019999999" mMin="6.55374998" type="GR" weight="0.2"/>
    <Geometry depth="0.0" dip="40.0" rake="-90.0" width="23.33587">
      <Trace>
-112.31893,41.03441,0.00000
-112.30114,41.01222,0.00000
-112.26485,40.98913,0.00000
-112.27149,40.96613,0.00000
-112.26916,40.94448,0.00000
-112.23646,40.87027,0.00000
-112.21624,40.85455,0.00000
-112.18363,40.81915,0.00000
-112.19486,40.79391,0.00000
-112.20348,40.75051,0.00000
-112.21373,40.73408,0.00000
-112.22972,40.72392,0.00000
</Trace>
    </Geometry>
  </Source>
  <Source id="281" name="Stansbury 40">
    <IncrementalMfd a="1.7717044" dMag="0.09833336" mMax="7.04093332" mMin="6.54916668" type="GR" weight="0.2"/>
    <Geometry depth="0.0" dip="40.0" rake="-90.0" width="23.33587">
      <Trace>
-112.65942,40.68951,0.00000
-112.68340,40.59402,0.00000
-112.67119,40.54227,0.00000
-112.66427,40.53490,0.00000
-112.68449,40.50166,0.00000
-112.69230,40.47552,0.00000
-112.67873,40.43105,0.00000
-112.68026,40.42449,0.00000
-112.66499,40.39466,0.00000
-112.54541,40.27617,0.00000
-112.52520,40.25020,0.00000
</Trace>
    </Geometry>
  </Source>
  <Source id="282" name="Oquirrh - Southern Oquirrh Mountains 40">
    <IncrementalMfd a="1.5077448" dMag="0.11166668" mMax="7.114266659999999" mMin="6.55583334" type="GR" weight="0.2"/>
    <Geometry depth="0.0" dip="40.0" rake="-90.0" width="23.33587">
      <Trace>
-112.25326,40.69473,0.00000
-112.24660,40.68619,0.00000
-112.24409,40.65295,0.00000
-112.25452,40.64963,0.00000
-112.25622,40.64118,0.00000
-112.26305,40.63795,0.00000
-112.25883,40.63148,0.00000
-112.25703,40.60462,0.00000
-112.20034,40.55548,0.00000
-112.20034,40.54433,0.00000
-112.23906,40.53526,0.00000
-112.25784,40.51774,0.00000
-112.30430,40.50078,0.00000
-112.34476,40.45990,0.00000
-112.31691,40.40194,0.00000
-112.27478,40.30910,0.00000
-112.25825,40.27052,0.00000
-112.22314,40.22889,0.00000
</Trace>
    </Geometry>
  </Source>
  <Source id="283" name="Strawberry 40">
    <IncrementalMfd a="1.2698064" dMag="0.10500002" mMax="6.8675999899999995" mMin="6.55250001" type="GR" weight="0.2"/>
    <Geometry depth="0.0" dip="40.0" rake="-90.0" width="23.33587">
      <Trace>
-111.21238,40.28982,0.00000
-111.18471,40.28928,0.00000
-111.16782,40.28362,0.00000
-111.14132,40.25730,0.00000
-111.10744,40.25209,0.00000
-111.10313,40.23808,0.00000
-111.10080,40.20178,0.00000
-111.11419,40.16782,0.00000
-111.11140,40.15371,0.00000
-111.11913,40.14338,0.00000
-111.11598,40.12236,0.00000
-111.14213,40.09047,0.00000
-111.14706,40.05615,0.00000
-111.13862,40.00755,0.00000
</Trace>
    </Geometry>
  </Source>
  <Source id="285" name="West Cache - Clarkston section 40">
    <IncrementalMfd a="2.0463051" dMag="0.07999992" mMax="6.62010004" mMin="6.53999996" type="GR" weight="0.2"/>
    <Geometry depth="0.0" dip="40.0" rake="-90.0" width="23.33587">
      <Trace>
-112.06657,41.89625,0.00000
-112.07013,41.89819,0.00000
-112.08070,41.91283,0.00000
-112.08927,41.92109,0.00000
-112.09216,41.93003,0.00000
-112.09834,41.93920,0.00000
-112.10303,41.94943,0.00000
-112.10191,41.95312,0.00000
-112.11048,41.97083,0.00000
-112.10936,41.98233,0.00000
-112.10979,41.99078,0.00000
-112.10667,41.99516,0.00000
-112.09572,41.99985,0.00000
-112.09353,42.00871,0.00000
-112.09103,42.01321,0.00000
-112.09065,42.03051,0.00000
-112.08408,42.05125,0.00000
-112.08076,42.07558,0.00000
-112.07820,42.08941,0.00000
</Trace>
    </Geometry>
  </Source>
  <Source id="286" name="West Cache - Wellsville section 40">
    <IncrementalMfd a="0.00029664705" floats="true" m="6.55" type="SINGLE" weight="0.2"/>
    <Geometry depth="0.0" dip="40.0" rake="-90.0" width="23.33587">
      <Trace>
-111.87531,41.57973,0.00000
-111.91807,41.60130,0.00000
-111.95148,41.62492,0.00000
-111.99946,41.68979,0.00000
-112.00980,41.69670,0.00000
-112.02291,41.72105,0.00000
</Trace>
    </Geometry>
  </Source>
  <Source id="287" name="Paragonah 40">
    <IncrementalMfd a="2.147697" dMag="0.125" mMax="6.6876" mMin="6.5625" type="GR" weight="0.2"/>
    <Geometry depth="0.0" dip="40.0" rake="-90.0" width="23.33587">
      <Trace>
-112.70164,37.97835,0.00000
-112.71494,37.94951,0.00000
-112.74746,37.91241,0.00000
-112.75195,37.88995,0.00000
-112.78816,37.83784,0.00000
-112.84296,37.80253,0.00000
-112.86929,37.77684,0.00000
</Trace>
    </Geometry>
  </Source>
  <Source id="477" name="Sevier - Toroweap (northern) 40">
    <IncrementalMfd a="1.7099055" dMag="0.10374999" mMax="7.2782250049999995" mMin="6.551874995" type="GR" weight="0.2"/>
    <Geometry depth="0.0" dip="40.0" rake="-90.0" width="23.33587">
      <Trace>
-112.29620,37.87458,0.00000
-112.33034,37.79678,0.00000
-112.33267,37.77298,0.00000
-112.32729,37.72680,0.00000
-112.33250,37.68412,0.00000
-112.35397,37.66499,0.00000
-112.37382,37.63597,0.00000
-112.38424,37.60291,0.00000
-112.39547,37.58575,0.00000
-112.40212,37.55566,0.00000
-112.42107,37.52242,0.00000
-112.52861,37.37975,0.00000
-112.53661,37.37894,0.00000
-112.54497,37.37122,0.00000
-112.55170,37.35289,0.00000
-112.56132,37.34085,0.00000
-112.56913,37.33752,0.00000
-112.62331,37.27886,0.00000
-112.66005,37.20268,0.00000
-112.66517,37.16908,0.00000
</Trace>
    </Geometry>
  </Source>
  <Source id="479" name="Hurricane (northern) 40">
    <IncrementalMfd a="1.4357765" dMag="0.086666665" mMax="6.9767666675" mMin="6.5433333325" type="GR" weight="0.2"/>
    <Geometry depth="0.0" dip="40.0" rake="-90.0" width="23.33587">
      <Trace>
-113.05462,37.66077,0.00000
-113.09164,37.61567,0.00000
-113.10520,37.58944,0.00000
-113.12784,37.56922,0.00000
-113.14509,37.56536,0.00000
-113.16396,37.55206,0.00000
-113.19738,37.50121,0.00000
-113.21436,37.48882,0.00000
-113.23026,37.42386,0.00000
-113.22775,37.40374,0.00000
-113.26620,37.33483,0.00000
-113.28227,37.29701,0.00000
</Trace>
    </Geometry>
  </Source>
  <Source id="284" name="Joes Valley 40">
    <IncrementalMfd a="1.6202512" dMag="0.125" mMax="6.9376" mMin="6.5625" type="GR" weight="0.2"/>
    <Geometry depth="0.0" dip="40.0" rake="-90.0" width="23.33587">
      <Trace>
-111.22218,39.59977,0.00000
-111.21831,39.53122,0.00000
-111.23071,39.50013,0.00000
-111.22810,39.46815,0.00000
-111.23260,39.43150,0.00000
-111.25721,39.35990,0.00000
-111.27042,39.30213,0.00000
-111.26961,39.25838,0.00000
-111.25739,39.18471,0.00000
</Trace>
    </Geometry>
  </Source>
  <Source id="274" name="Hansel Valley 40">
    <IncrementalMfd a="0.00019073601" floats="true" m="6.55" type="SINGLE" weight="0.2"/>
    <Geometry depth="0.0" dip="40.0" rake="-90.0" width="23.33587">
      <Trace>
-112.75555,41.68394,0.00000
-112.74863,41.71027,0.00000
-112.73273,41.73938,0.00000
-112.72842,41.78097,0.00000
-112.72060,41.79813,0.00000
</Trace>
    </Geometry>
  </Source>
  <Source id="272" name="East Cache 60">
    <IncrementalMfd a="1.1817492" dMag="0.10124999" mMax="7.259475005" mMin="6.550624995" type="GR" weight="0.2"/>
    <Geometry depth="0.0" dip="60.0" rake="-90.0" width="17.320515">
      <Trace>
-111.69625,42.13224,0.00000
-111.72994,42.04950,0.00000
-111.73632,42.00063,0.00000
-111.76256,41.97511,0.00000
-111.78744,41.93289,0.00000
-111.79382,41.91411,0.00000
-111.78960,41.90944,0.00000
-111.79112,41.89489,0.00000
-111.80235,41.88015,0.00000
-111.81458,41.87575,0.00000
-111.79067,41.83119,0.00000
-111.77531,41.78025,0.00000
-111.79095,41.74360,0.00000
-111.80559,41.64073,0.00000
-111.79903,41.61729,0.00000
-111.78367,41.59429,0.00000
-111.77531,41.49995,0.00000
-111.75959,41.44758,0.00000
-111.76534,41.42189,0.00000
</Trace>
    </Geometry>
  </Source>
  <Source id="273" name="Morgan 60">
    <IncrementalMfd a="3.1853093e-05" floats="true" m="6.51" type="SINGLE" weight="0.2"/>
    <Geometry depth="0.0" dip="60.0" rake="-90.0" width="17.320515">
      <Trace>
-111.72213,41.15147,0.00000
-111.70596,41.10673,0.00000
-111.67146,41.07663,0.00000
-111.66795,41.02731,0.00000
-111.65457,41.00961,0.00000
</Trace>
    </Geometry>
  </Source>
  <Source id="275" name="North Promontory 60">
    <IncrementalMfd a="1.5201766" dMag="0.11500001" mMax="6.672599995000001" mMin="6.557500005" type="GR" weight="0.2"/>
    <Geometry depth="0.0" dip="60.0" rake="-90.0" width="17.320515">
      <Trace>
-112.54981,41.90154,0.00000
-112.54937,41.87926,0.00000
-112.55628,41.85455,0.00000
-112.55476,41.78897,0.00000
-112.55952,41.76606,0.00000
-112.59357,41.69922,0.00000
-112.61729,41.67361,0.00000
</Trace>
    </Geometry>
  </Source>
  <Source id="277" name="Great Salt Lake - Promontory section 60">
    <IncrementalMfd a="1.6866705" dMag="0.09833336" mMax="7.04093332" mMin="6.54916668" type="GR" weight="0.2"/>
    <Geometry depth="0.0" dip="60.0" rake="-90.0" width="17.320515">
      <Trace>
-112.83550,41.53418,0.00000
-112.80316,41.49349,0.00000
-112.77477,41.46743,0.00000
-112.70416,41.43572,0.00000
-112.65448,41.39826,0.00000
-112.57551,41.38820,0.00000
-112.54659,41.37562,0.00000
-112.53293,41.34651,0.00000
-112.51271,41.32450,0.00000
-112.51181,41.26314,0.00000
-112.50211,41.23700,0.00000
-112.48944,41.21498,0.00000
-112.45800,41.19190,0.00000
</Trace>
    </Geometry>
  </Source>
  <Source id="278" name="Great Salt Lake - Fremont Island section 60">
    <IncrementalMfd a="1.7390506" dMag="0.08249998" mMax="6.78885001" mMin="6.54124999" type="GR" weight="0.2"/>
    <Geometry depth="0.0" dip="60.0" rake="-90.0" width="17.320515">
      <Trace>
-112.52106,41.21004,0.00000
-112.51936,41.19926,0.00000
-112.49142,41.17833,0.00000
-112.45189,41.17132,0.00000
-112.44012,41.16162,0.00000
-112.41326,41.15156,0.00000
-112.36376,41.09325,0.00000
-112.35370,41.06019,0.00000
-112.32657,41.02605,0.00000
-112.31839,41.00368,0.00000
-112.30527,40.99272,0.00000
</Trace>
    </Geometry>
  </Source>
  <Source id="279" name="Great Salt Lake - Antelope Island section 60">
    <IncrementalMfd a="1.791742" dMag="0.10749996" mMax="6.876350019999999" mMin="6.55374998" type="GR" weight="0.2"/>
    <Geometry depth="0.0" dip="60.0" rake="-90.0" width="17.320515">
      <Trace>
-112.31893,41.03441,0.00000
-112.30114,41.01222,0.00000
-112.26485,40.98913,0.00000
-112.27149,40.96613,0.00000
-112.26916,40.94448,0.00000
-112.23646,40.87027,0.00000
-112.21624,40.85455,0.00000
-112.18363,40.81915,0.00000
-112.19486,40.79391,0.00000
-112.20348,40.75051,0.00000
-112.21373,40.73408,0.00000
-112.22972,40.72392,0.00000
</Trace>
    </Geometry>
  </Source>
  <Source id="281" name="Stansbury 60">
    <IncrementalMfd a="1.512778" dMag="0.09833336" mMax="7.04093332" mMin="6.54916668" type="GR" weight="0.2"/>
    <Geometry depth="0.0" dip="60.0" rake="-90.0" width="17.320515">
      <Trace>
-112.65942,40.68951,0.00000
-112.68340,40.59402,0.00000
-112.67119,40.54227,0.00000
-112.66427,40.53490,0.00000
-112.68449,40.50166,0.00000
-112.69230,40.47552,0.00000
-112.67873,40.43105,0.00000
-112.68026,40.42449,0.00000
-112.66499,40.39466,0.00000
-112.54541,40.27617,0.00000
-112.52520,40.25020,0.00000
</Trace>
    </Geometry>
  </Source>
  <Source id="282" name="Oquirrh - Southern Oquirrh Mountains 60">
    <IncrementalMfd a="1.2488183" dMag="0.11166668" mMax="7.114266659999999" mMin="6.55583334" type="GR" weight="0.2"/>
    <Geometry depth="0.0" dip="60.0" rake="-90.0" width="17.320515">
      <Trace>
-112.25326,40.69473,0.00000
-112.24660,40.68619,0.00000
-112.24409,40.65295,0.00000
-112.25452,40.64963,0.00000
-112.25622,40.64118,0.00000
-112.26305,40.63795,0.00000
-112.25883,40.63148,0.00000
-112.25703,40.60462,0.00000
-112.20034,40.55548,0.00000
-112.20034,40.54433,0.00000
-112.23906,40.53526,0.00000
-112.25784,40.51774,0.00000
-112.30430,40.50078,0.00000
-112.34476,40.45990,0.00000
-112.31691,40.40194,0.00000
-112.27478,40.30910,0.00000
-112.25825,40.27052,0.00000
-112.22314,40.22889,0.00000
</Trace>
    </Geometry>
  </Source>
  <Source id="283" name="Strawberry 60">
    <IncrementalMfd a="1.0108799" dMag="0.105" mMax="6.8675999999999995" mMin="6.5525" type="GR" weight="0.2"/>
    <Geometry depth="0.0" dip="60.0" rake="-90.0" width="17.320515">
      <Trace>
-111.21238,40.28982,0.00000
-111.18471,40.28928,0.00000
-111.16782,40.28362,0.00000
-111.14132,40.25730,0.00000
-111.10744,40.25209,0.00000
-111.10313,40.23808,0.00000
-111.10080,40.20178,0.00000
-111.11419,40.16782,0.00000
-111.11140,40.15371,0.00000
-111.11913,40.14338,0.00000
-111.11598,40.12236,0.00000
-111.14213,40.09047,0.00000
-111.14706,40.05615,0.00000
-111.13862,40.00755,0.00000
</Trace>
    </Geometry>
  </Source>
  <Source id="285" name="West Cache - Clarkston section 60">
    <IncrementalMfd a="1.7873787" dMag="0.07999992" mMax="6.62010004" mMin="6.53999996" type="GR" weight="0.2"/>
    <Geometry depth="0.0" dip="60.0" rake="-90.0" width="17.320515">
      <Trace>
-112.06657,41.89625,0.00000
-112.07013,41.89819,0.00000
-112.08070,41.91283,0.00000
-112.08927,41.92109,0.00000
-112.09216,41.93003,0.00000
-112.09834,41.93920,0.00000
-112.10303,41.94943,0.00000
-112.10191,41.95312,0.00000
-112.11048,41.97083,0.00000
-112.10936,41.98233,0.00000
-112.10979,41.99078,0.00000
-112.10667,41.99516,0.00000
-112.09572,41.99985,0.00000
-112.09353,42.00871,0.00000
-112.09103,42.01321,0.00000
-112.09065,42.03051,0.00000
-112.08408,42.05125,0.00000
-112.08076,42.07558,0.00000
-112.07820,42.08941,0.00000
</Trace>
    </Geometry>
  </Source>
  <Source id="286" name="West Cache - Wellsville section 60">
    <IncrementalMfd a="0.00016342317" floats="true" m="6.55" type="SINGLE" weight="0.2"/>
    <Geometry depth="0.0" dip="60.0" rake="-90.0" width="17.320515">
      <Trace>
-111.87531,41.57973,0.00000
-111.91807,41.60130,0.00000
-111.95148,41.62492,0.00000
-111.99946,41.68979,0.00000
-112.00980,41.69670,0.00000
-112.02291,41.72105,0.00000
</Trace>
    </Geometry>
  </Source>
  <Source id="287" name="Paragonah 60">
    <IncrementalMfd a="1.8887706" dMag="0.125" mMax="6.6876" mMin="6.5625" type="GR" weight="0.2"/>
    <Geometry depth="0.0" dip="60.0" rake="-90.0" width="17.320515">
      <Trace>
-112.70164,37.97835,0.00000
-112.71494,37.94951,0.00000
-112.74746,37.91241,0.00000
-112.75195,37.88995,0.00000
-112.78816,37.83784,0.00000
-112.84296,37.80253,0.00000
-112.86929,37.77684,0.00000
</Trace>
    </Geometry>
  </Source>
  <Source id="477" name="Sevier - Toroweap (northern) 60">
    <IncrementalMfd a="1.4509791" dMag="0.10374999" mMax="7.2782250049999995" mMin="6.551874995" type="GR" weight="0.2"/>
    <Geometry depth="0.0" dip="60.0" rake="-90.0" width="17.320515">
      <Trace>
-112.29620,37.87458,0.00000
-112.33034,37.79678,0.00000
-112.33267,37.77298,0.00000
-112.32729,37.72680,0.00000
-112.33250,37.68412,0.00000
-112.35397,37.66499,0.00000
-112.37382,37.63597,0.00000
-112.38424,37.60291,0.00000
-112.39547,37.58575,0.00000
-112.40212,37.55566,0.00000
-112.42107,37.52242,0.00000
-112.52861,37.37975,0.00000
-112.53661,37.37894,0.00000
-112.54497,37.37122,0.00000
-112.55170,37.35289,0.00000
-112.56132,37.34085,0.00000
-112.56913,37.33752,0.00000
-112.62331,37.27886,0.00000
-112.66005,37.20268,0.00000
-112.66517,37.16908,0.00000
</Trace>
    </Geometry>
  </Source>
  <Source id="479" name="Hurricane (northern) 60">
    <IncrementalMfd a="1.1768501" dMag="0.086666665" mMax="6.9767666675" mMin="6.5433333325" type="GR" weight="0.2"/>
    <Geometry depth="0.0" dip="60.0" rake="-90.0" width="17.320515">
      <Trace>
-113.05462,37.66077,0.00000
-113.09164,37.61567,0.00000
-113.10520,37.58944,0.00000
-113.12784,37.56922,0.00000
-113.14509,37.56536,0.00000
-113.16396,37.55206,0.00000
-113.19738,37.50121,0.00000
-113.21436,37.48882,0.00000
-113.23026,37.42386,0.00000
-113.22775,37.40374,0.00000
-113.26620,37.33483,0.00000
-113.28227,37.29701,0.00000
</Trace>
    </Geometry>
  </Source>
  <Source id="274" name="Hansel Valley 60">
    <IncrementalMfd a="0.00010507667" floats="true" m="6.55" type="SINGLE" weight="0.2"/>
    <Geometry depth="0.0" dip="60.0" rake="-90.0" width="17.320515">
      <Trace>
-112.75555,41.68394,0.00000
-112.74863,41.71027,0.00000
-112.73273,41.73938,0.00000
-112.72842,41.78097,0.00000
-112.72060,41.79813,0.00000
</Trace>
    </Geometry>
  </Source>
  <Source id="284" name="Joes Valley 60">
    <IncrementalMfd a="1.3613247" dMag="0.125" mMax="6.9376" mMin="6.5625" type="GR" weight="0.2"/>
    <Geometry depth="0.0" dip="60.0" rake="-90.0" width="17.320515">
      <Trace>
-111.22218,39.59977,0.00000
-111.21831,39.53122,0.00000
-111.23071,39.50013,0.00000
-111.22810,39.46815,0.00000
-111.23260,39.43150,0.00000
-111.25721,39.35990,0.00000
-111.27042,39.30213,0.00000
-111.26961,39.25838,0.00000
-111.25739,39.18471,0.00000
</Trace>
    </Geometry>
  </Source>
</FaultSourceSet>
